__init__.py
buildpack.py
main.py
shonku_buildpack-0.0.5.dist-info/METADATA
shonku_buildpack-0.0.5.dist-info/WHEEL
shonku_buildpack-0.0.5.dist-info/top_level.txt
shonku_buildpack-0.0.5.dist-info/RECORD
